ephemerality/__init__.py
ephemerality/__main__.py
ephemerality/rest/__init__.py
ephemerality/rest/api.py
ephemerality/rest/api_versions/__init__.py
ephemerality/rest/api_versions/api11.py
ephemerality/rest/api_versions/api_template.py
ephemerality/rest/runner.py
ephemerality/scripts/__init__.py
ephemerality/scripts/ephemerality_api.py
ephemerality/scripts/ephemerality_cmd.py
ephemerality/src/__init__.py
ephemerality/src/data_processing.py
ephemerality/src/ephemerality_computation.py
ephemerality/src/utils.py
ephemerality-2.0.2.dist-info/LICENSE
ephemerality-2.0.2.dist-info/METADATA
ephemerality-2.0.2.dist-info/WHEEL
ephemerality-2.0.2.dist-info/RECORD
