Metadata-Version: 2.1
Name: ephemerality
Version: 2.0.2
Summary: Module for computing ephemerality metrics for temporal activity vectors.
Home-page: https://github.com/HPAI-BSC/ephemerality
License: MIT
Author: Dmitry Gnatyshak
Author-email: dmitry.gnatyshak@bsc.es
Requires-Python: >=3.10,<4.0
Classifier: License :: OSI Approved :: MIT License
Classifier: Programming Language :: Python
Classifier: Programming Language :: Python :: 3
Classifier: Programming Language :: Python :: 3.10
Classifier: Programming Language :: Python :: 3.11
Classifier: Programming Language :: Python :: 3.12
Requires-Dist: fastapi (>=0.110.2,<0.111.0)
Requires-Dist: matplotlib (>=3.8.4,<4.0.0)
Requires-Dist: numpy (>=1.24.2,<2.0.0)
Requires-Dist: pydantic (>=2.7.1,<3.0.0)
Requires-Dist: uvicorn (>=0.22.0,<0.23.0)
Project-URL: Repository, https://github.com/HPAI-BSC/ephemerality
